mTSPsolvers/__init__.py
mTSPsolvers/solver.py
mTSPsolvers/utils.py
mTSPsolvers/solvers/__init__.py
mTSPsolvers/solvers/cplex.py
mTSPsolvers/solvers/crossover.py
mTSPsolvers/solvers/lkh.py
mTSPsolvers/solvers/ortools.py
mTSPsolvers/solvers/twophase.py
mtspsolvers-0.0.9.dist-info/LICENSE
mtspsolvers-0.0.9.dist-info/METADATA
mtspsolvers-0.0.9.dist-info/WHEEL
mtspsolvers-0.0.9.dist-info/top_level.txt
mtspsolvers-0.0.9.dist-info/RECORD
